wabee/__init__.py
wabee/cli/README.md
wabee/cli/__init__.py
wabee/cli/commands/create_tool.py
wabee/cli/main.py
wabee/cli/tools/build_tool_service.py
wabee/cli/tools/create_tool_service.py
wabee/cli/tools/templates/js_server.js
wabee/cli/tools/templates/python_server.py
wabee/rpc/client.py
wabee/rpc/loader.py
wabee/rpc/protos/tool_service.proto
wabee/rpc/protos/tool_service_pb2.py
wabee/rpc/protos/tool_service_pb2.pyi
wabee/rpc/protos/tool_service_pb2_grpc.py
wabee/rpc/schema.py
wabee/rpc/server.py
wabee/tools/__init__.py
wabee/tools/base_model.py
wabee/tools/base_tool.py
wabee/tools/simple_tool.py
wabee/tools/tool_error.py
wabee-0.3.2.dist-info/LICENSE
wabee-0.3.2.dist-info/METADATA
wabee-0.3.2.dist-info/WHEEL
wabee-0.3.2.dist-info/entry_points.txt
wabee-0.3.2.dist-info/RECORD
