Metadata-Version: 2.1
Name: wabee
Version: 0.3.2
Summary: Wabee AI Software Development Kit
License: Apache License V2
Keywords: wabee,wabee ai,ai agents,generative ai,llm agents
Author: Developers
Author-email: developers@wabee.ai
Maintainer: Developers
Maintainer-email: developers@wabee.ai
Requires-Python: >=3.10,<3.13
Classifier: Development Status :: 5 - Production/Stable
Classifier: Intended Audience :: Developers
Classifier: License :: Other/Proprietary License
Classifier: Natural Language :: Portuguese (Brazilian)
Classifier: Operating System :: Unix
Classifier: Programming Language :: Python :: 3
Classifier: Programming Language :: Python :: 3.10
Classifier: Programming Language :: Python :: 3.11
Classifier: Programming Language :: Python :: 3.12
Classifier: Topic :: Scientific/Engineering :: Artificial Intelligence
Requires-Dist: chardet (>=5.2.0,<6.0.0)
Requires-Dist: grpcio (>=1.68.0,<2.0.0)
Requires-Dist: grpcio-tools (>=1.68.0,<2.0.0)
Requires-Dist: inquirer (>=3.4.0,<4.0.0)
Requires-Dist: pydantic (>=2.7.4,<3.0.0)
Requires-Dist: pyyaml (>=6.0.1,<7.0.0)
Requires-Dist: requests (>=2.32.3,<3.0.0)
Requires-Dist: restrictedpython (>=7.1,<8.0)
Requires-Dist: typing-extensions (>=4.12.2,<5.0.0)
